bit_saver/__init__.py
bit_saver/bit_saver.py
bit_saver-0.11.dist-info/METADATA
bit_saver-0.11.dist-info/WHEEL
bit_saver-0.11.dist-info/top_level.txt
bit_saver-0.11.dist-info/RECORD
