Metadata-Version: 2.1
Name: bit-saver
Version: 0.11
Summary: A package to save OHLCV data from Upbit exchange to local storage.
Home-page: https://github.com/choisun0924/bit-saver
Author: Choi Sun
Author-email: choisun@tritech.co.kr
License: MIT
Classifier: License :: OSI Approved :: MIT License
Classifier: Programming Language :: Python :: 3
Classifier: Programming Language :: Python :: 3.9
Requires-Dist: pyupbit
Requires-Dist: pandas
